odoo/addons/account_reconcile_reconciliation_date/README.rst
odoo/addons/account_reconcile_reconciliation_date/__init__.py
odoo/addons/account_reconcile_reconciliation_date/__manifest__.py
odoo/addons/account_reconcile_reconciliation_date/i18n/account_reconcile_reconciliation_date.pot
odoo/addons/account_reconcile_reconciliation_date/models/__init__.py
odoo/addons/account_reconcile_reconciliation_date/models/account_full_reconcile.py
odoo/addons/account_reconcile_reconciliation_date/models/account_invoice.py
odoo/addons/account_reconcile_reconciliation_date/models/account_payment.py
odoo/addons/account_reconcile_reconciliation_date/readme/CONTRIBUTORS.rst
odoo/addons/account_reconcile_reconciliation_date/readme/DESCRIPTION.rst
odoo/addons/account_reconcile_reconciliation_date/static/description/icon.png
odoo/addons/account_reconcile_reconciliation_date/static/description/index.html
odoo/addons/account_reconcile_reconciliation_date/tests/__init__.py
odoo/addons/account_reconcile_reconciliation_date/tests/test_account_reconcile_reconciliation_date.py
odoo/addons/account_reconcile_reconciliation_date/views/account_invoice.xml
odoo/addons/account_reconcile_reconciliation_date/views/account_payment.xml
odoo12_addon_account_reconcile_reconciliation_date-12.0.1.1.0.dist-info/METADATA
odoo12_addon_account_reconcile_reconciliation_date-12.0.1.1.0.dist-info/WHEEL
odoo12_addon_account_reconcile_reconciliation_date-12.0.1.1.0.dist-info/top_level.txt
odoo12_addon_account_reconcile_reconciliation_date-12.0.1.1.0.dist-info/RECORD
