Metadata-Version: 2.1
Name: odoo12-addon-account-reconcile-reconciliation-date
Version: 12.0.1.1.0
Summary: Track Reconciliation Date of Payments and Invoices
Home-page: http://www.github.com/OCA/account-reconcile
Author: Open Source Integrators, Odoo Community Association (OCA)
Author-email: support@odoo-community.org
License: AGPL-3
Platform: UNKNOWN
Classifier: Programming Language :: Python
Classifier: Framework :: Odoo
Classifier: License :: OSI Approved :: GNU Affero General Public License v3
Requires-Python: >=3.5
Requires-Dist: odoo (<12.1dev,>=12.0a)
